django_externaltestserver-0.2.5.dist-info/DESCRIPTION.rst
django_externaltestserver-0.2.5.dist-info/METADATA
django_externaltestserver-0.2.5.dist-info/RECORD
django_externaltestserver-0.2.5.dist-info/WHEEL
django_externaltestserver-0.2.5.dist-info/metadata.json
django_externaltestserver-0.2.5.dist-info/top_level.txt
externaltestserver/__init__.py
externaltestserver/testcases.py
externaltestserver/management/__init__.py
externaltestserver/management/commands/__init__.py
externaltestserver/management/commands/livetestserver.py
